Workbook

Sheet Loan Calculator
A1: Loan Calculator | M1: Additional Info | O1: Per Year (up to 50 years)
M2: Payment per period | O2: Year | P2: Interest Payments | Q2: Principal payments | R2: Total Paid | S2: Total interest Paid | T2: Total Principal Paid
A3: Loan term : | B3: 30 | C3: Years | E3: Loan Amount : | F3: 250000 | H3: Interest Rate : | I3: 0.07 | M3: =calcs!H8 -> 1663.2562 | O3: =IF(I23="","",1) -> 1 | P3: =IF(O3="","",SUBTOTAL(9,E12:E23)) -> 17419.55 | Q3: =IF(P3="","",SUBTOTAL(9,F12:F23)) -> 2539.5246 | R3: =IF(P3="","",P3+Q3) -> 19959.075 | S3: =IF(P3="","",P3) -> 17419.55 | T3: =IF(S3="","",Q3) -> 2539.5246
B4: 0 | C4: Months | O4: =IF(AND(I35="",H24=""),"",2) -> 2 | P4: =IF(O4="","",SUBTOTAL(9,E24:E35)) -> 17235.968 | Q4: =IF(P4="","",SUBTOTAL(9,F24:F35)) -> 2723.107 | R4: =IF(OR(P4="",Q4=""),"",R3+(P4+Q4)) -> 39918.15 | S4: =IF(P4="","",SUM($P$3:P4)) -> 34655.518 | T4: =IF(S4="","",SUM($Q$3:Q4)) -> 5262.6316
M5: Total Interest Paid | O5: =IF(AND(I47="",H36=""),"",3) -> 3 | P5: =IF(O5="","",SUBTOTAL(9,E36:E47)) -> 17039.114 | Q5: =IF(P5="","",SUBTOTAL(9,F36:F47)) -> 2919.9606 | R5: =IF(OR(P5="",Q5=""),"",R4+(P5+Q5)) -> 59877.225 | S5: =IF(P5="","",SUM($P$3:P5)) -> 51694.632 | T5: =IF(S5="","",SUM($Q$3:Q5)) -> 8182.5922
C6: Optional : If making extra payments / overpayments | M6: =SUBTOTAL(9,E12:E1011) -> 348772.25 | O6: =IF(AND(I59="",H48=""),"",4) -> 4 | P6: =IF(O6="","",SUBTOTAL(9,E48:E59)) -> 16828.03 | Q6: =IF(P6="","",SUBTOTAL(9,F48:F59)) -> 3131.0448 | R6: =IF(OR(P6="",Q6=""),"",R5+(P6+Q6)) -> 79836.299 | S6: =IF(P6="","",SUM($P$3:P6)) -> 68522.662 | T6: =IF(S6="","",SUM($Q$3:Q6)) -> 11313.637
O7: =IF(AND(I71="",H60=""),"",5) -> 5 | P7: =IF(O7="","",SUBTOTAL(9,E60:E71)) -> 16601.687 | Q7: =IF(P7="","",SUBTOTAL(9,F60:F71)) -> 3357.3883 | R7: =IF(OR(P7="",Q7=""),"",R6+(P7+Q7)) -> 99795.374 | S7: =IF(P7="","",SUM($P$3:P7)) -> 85124.349 | T7: =IF(S7="","",SUM($Q$3:Q7)) -> 14671.025
A8: Extra payment every month : | D8: 0 | M8: Total Principal Paid | O8: =IF(AND(I83="",H72=""),"",6) -> 6 | P8: =IF(O8="","",SUBTOTAL(9,E72:E83)) -> 16358.981 | Q8: =IF(P8="","",SUBTOTAL(9,F72:F83)) -> 3600.0942 | R8: =IF(OR(P8="",Q8=""),"",R7+(P8+Q8)) -> 119754.45 | S8: =IF(P8="","",SUM($P$3:P8)) -> 101483.33 | T8: =IF(S8="","",SUM($Q$3:Q8)) -> 18271.12
M9: =SUBTOTAL(9,F12:F1011) -> 250000 | O9: =IF(AND(I95="",H84=""),"",7) -> 7 | P9: =IF(O9="","",SUBTOTAL(9,E84:E95)) -> 16098.73 | Q9: =IF(P9="","",SUBTOTAL(9,F84:F95)) -> 3860.3453 | R9: =IF(OR(P9="",Q9=""),"",R8+(P9+Q9)) -> 139713.52 | S9: =IF(P9="","",SUM($P$3:P9)) -> 117582.06 | T9: =IF(S9="","",SUM($Q$3:Q9)) -> 22131.465
D10: Monthly Amortization Table | O10: =IF(AND(I107="",H96=""),"",8) -> 8 | P10: =IF(O10="","",SUBTOTAL(9,E96:E107)) -> 15819.665 | Q10: =IF(P10="","",SUBTOTAL(9,F96:F107)) -> 4139.41 | R10: =IF(OR(P10="",Q10=""),"",R9+(P10+Q10)) -> 159672.6 | S10: =IF(P10="","",SUM($P$3:P10)) -> 133401.72 | T10: =IF(S10="","",SUM($Q$3:Q10)) -> 26270.875
D11: Month | E11: Interest | F11: Principal | G11: Ending Balance | H11: Total Amount Paid | M11: Total Amount Paid | O11: =IF(AND(I119="",H108=""),"",9) -> 9 | P11: =IF(O11="","",SUBTOTAL(9,E108:E119)) -> 15520.427 | Q11: =IF(P11="","",SUBTOTAL(9,F108:F119)) -> 4438.6482 | R11: =IF(OR(P11="",Q11=""),"",R10+(P11+Q11)) -> 179631.67 | S11: =IF(P11="","",SUM($P$3:P11)) -> 148922.15 | T11: =IF(S11="","",SUM($Q$3:Q11)) -> 30709.523
D12: =IF(V12<=calcs!$F$4,'Loan Calculator'!V12,"") -> 1 | E12: =IF(D8<=0,$M$3-F12,$M$3-F12+D8) -> 1458.3333 | F12: {=_xlfn.IFS(D8=0,M3-(F3*calcs!H3),D8>0,D8+M3-(F3*calcs!H3))} -> 204.9229 | G12: =F3-F12 -> 249795.08 | H12: =IF((E12+F12)="","",E12+F12) -> 1663.2562 | I12: {=_xlfn.IFS(OR(D12="",E12="",F12=""),"",MOD(D12,12)<>0,"",MOD(D12,12)=0,"Year End"&" "&D12/12)} | M12: =M6+M9 -> 598772.25 | O12: =IF(AND(I131="",H120=""),"",10) -> 10 | P12: =IF(O12="","",SUBTOTAL(9,E120:E131)) -> 15199.556 | Q12: =IF(P12="","",SUBTOTAL(9,F120:F131)) -> 4759.5185 | R12: =IF(OR(P12="",Q12=""),"",R11+(P12+Q12)) -> 199590.75 | S12: =IF(P12="","",SUM($P$3:P12)) -> 164121.71 | T12: =IF(S12="","",SUM($Q$3:Q12)) -> 35469.041 | V12: 1
D13: =IF(V13<=calcs!$F$4,'Loan Calculator'!V13,"") -> 2 | E13: {=_xlfn.IFS(F13="","",G12<F12,G12*calcs!$H$3,$D$8<=0,$M$3-F13,$D$8>0,$M$3-F13+$D$8,G12<F12,G13*calcs!$H$3)} -> 1457.1379 | F13: {=_xlfn.IFS(F12="","",G12=0,"",G12<1,"",G12<F12,G12,AND(G12>0,$D$8>0),$D$8+($M$3-(G12*calcs!$H$3)),G12>0,$M$3-(G12*calcs!$H$3))} -> 206.11829 | G13: {=_xlfn.IFS(F13="","",G12-F13<1,0,ISBLANK(F13)=TRUE,"",G12-F13>1,G12-F13)} -> 249588.96 | H13: =IF(OR(H12=0,H12="",E13="",F13=""),"",H12+E13+F13) -> 3326.5125 | I13: {=_xlfn.IFS(OR(D13="",E13="",F13=""),"",MOD(D13,12)<>0,"",MOD(D13,12)=0,"Year End"&" "&D13/12)} | O13: =IF(AND(I143="",H132=""),"",11) -> 11 | P13: =IF(O13="","",SUBTOTAL(9,E132:E143)) -> 14855.49 | Q13: =IF(P13="","",SUBTOTAL(9,F132:F143)) -> 5103.5845 | R13: =IF(OR(P13="",Q13=""),"",R12+(P13+Q13)) -> 219549.82 | S13: =IF(P13="","",SUM($P$3:P13)) -> 178977.2 | T13: =IF(S13="","",SUM($Q$3:Q13)) -> 40572.626 | V13: 2
D14: =IF(V14<=calcs!$F$4,'Loan Calculator'!V14,"") -> 3 | E14: {=_xlfn.IFS(F14="","",G13<F13,G13*calcs!$H$3,$D$8<=0,$M$3-F14,$D$8>0,$M$3-F14+$D$8,G13<F13,G14*calcs!$H$3)} -> 1455.9356 | F14: {=_xlfn.IFS(F13="","",G13=0,"",G13<1,"",G13<F13,G13,AND(G13>0,$D$8>0),$D$8+($M$3-(G13*calcs!$H$3)),G13>0,$M$3-(G13*calcs!$H$3))} -> 207.32064 | G14: {=_xlfn.IFS(F14="","",G13-F14<1,0,ISBLANK(F14)=TRUE,"",G13-F14>1,G13-F14)} -> 249381.64 | H14: =IF(OR(H13=0,H13="",E14="",F14=""),"",H13+E14+F14) -> 4989.7687 | I14: {=_xlfn.IFS(OR(D14="",E14="",F14=""),"",MOD(D14,12)<>0,"",MOD(D14,12)=0,"Year End"&" "&D14/12)} | O14: =IF(AND(I155="",H144=""),"",12) -> 12 | P14: =IF(O14="","",SUBTOTAL(9,E144:E155)) -> 14486.552 | Q14: =IF(P14="","",SUBTOTAL(9,F144:F155)) -> 5472.523 | R14: =IF(OR(P14="",Q14=""),"",R13+(P14+Q14)) -> 239508.9 | S14: =IF(P14="","",SUM($P$3:P14)) -> 193463.75 | T14: =IF(S14="","",SUM($Q$3:Q14)) -> 46045.149 | V14: 3
D15: =IF(V15<=calcs!$F$4,'Loan Calculator'!V15,"") -> 4 | E15: {=_xlfn.IFS(F15="","",G14<F14,G14*calcs!$H$3,$D$8<=0,$M$3-F15,$D$8>0,$M$3-F15+$D$8,G14<F14,G15*calcs!$H$3)} -> 1454.7262 | F15: {=_xlfn.IFS(F14="","",G14=0,"",G14<1,"",G14<F14,G14,AND(G14>0,$D$8>0),$D$8+($M$3-(G14*calcs!$H$3)),G14>0,$M$3-(G14*calcs!$H$3))} -> 208.53002 | G15: {=_xlfn.IFS(F15="","",G14-F15<1,0,ISBLANK(F15)=TRUE,"",G14-F15>1,G14-F15)} -> 249173.11 | H15: =IF(OR(H14=0,H14="",E15="",F15=""),"",H14+E15+F15) -> 6653.025 | I15: {=_xlfn.IFS(OR(D15="",E15="",F15=""),"",MOD(D15,12)<>0,"",MOD(D15,12)=0,"Year End"&" "&D15/12)} | O15: =IF(AND(I167="",H156=""),"",13) -> 13 | P15: =IF(O15="","",SUBTOTAL(9,E156:E167)) -> 14090.943 | Q15: =IF(P15="","",SUBTOTAL(9,F156:F167)) -> 5868.1321 | R15: =IF(OR(P15="",Q15=""),"",R14+(P15+Q15)) -> 259467.97 | S15: =IF(P15="","",SUM($P$3:P15)) -> 207554.69 | T15: =IF(S15="","",SUM($Q$3:Q15)) -> 51913.281 | V15: 4
D16: =IF(V16<=calcs!$F$4,'Loan Calculator'!V16,"") -> 5 | E16: {=_xlfn.IFS(F16="","",G15<F15,G15*calcs!$H$3,$D$8<=0,$M$3-F16,$D$8>0,$M$3-F16+$D$8,G15<F15,G16*calcs!$H$3)} -> 1453.5098 | F16: {=_xlfn.IFS(F15="","",G15=0,"",G15<1,"",G15<F15,G15,AND(G15>0,$D$8>0),$D$8+($M$3-(G15*calcs!$H$3)),G15>0,$M$3-(G15*calcs!$H$3))} -> 209.74644 | G16: {=_xlfn.IFS(F16="","",G15-F16<1,0,ISBLANK(F16)=TRUE,"",G15-F16>1,G15-F16)} -> 248963.36 | H16: =IF(OR(H15=0,H15="",E16="",F16=""),"",H15+E16+F16) -> 8316.2812 | I16: {=_xlfn.IFS(OR(D16="",E16="",F16=""),"",MOD(D16,12)<>0,"",MOD(D16,12)=0,"Year End"&" "&D16/12)} | O16: =IF(AND(I179="",H168=""),"",14) -> 14 | P16: =IF(O16="","",SUBTOTAL(9,E168:E179)) -> 13666.735 | Q16: =IF(P16="","",SUBTOTAL(9,F168:F179)) -> 6292.3399 | R16: =IF(OR(P16="",Q16=""),"",R15+(P16+Q16)) -> 279427.05 | S16: =IF(P16="","",SUM($P$3:P16)) -> 221221.43 | T16: =IF(S16="","",SUM($Q$3:Q16)) -> 58205.621 | V16: 5
D17: =IF(V17<=calcs!$F$4,'Loan Calculator'!V17,"") -> 6 | E17: {=_xlfn.IFS(F17="","",G16<F16,G16*calcs!$H$3,$D$8<=0,$M$3-F17,$D$8>0,$M$3-F17+$D$8,G16<F16,G17*calcs!$H$3)} -> 1452.2863 | F17: {=_xlfn.IFS(F16="","",G16=0,"",G16<1,"",G16<F16,G16,AND(G16>0,$D$8>0),$D$8+($M$3-(G16*calcs!$H$3)),G16>0,$M$3-(G16*calcs!$H$3))} -> 210.96996 | G17: {=_xlfn.IFS(F17="","",G16-F17<1,0,ISBLANK(F17)=TRUE,"",G16-F17>1,G16-F17)} -> 248752.39 | H17: =IF(OR(H16=0,H16="",E17="",F17=""),"",H16+E17+F17) -> 9979.5374 | I17: {=_xlfn.IFS(OR(D17="",E17="",F17=""),"",MOD(D17,12)<>0,"",MOD(D17,12)=0,"Year End"&" "&D17/12)} | O17: =IF(AND(I191="",H180=""),"",15) -> 15 | P17: =IF(O17="","",SUBTOTAL(9,E180:E191)) -> 13211.861 | Q17: =IF(P17="","",SUBTOTAL(9,F180:F191)) -> 6747.2136 | R17: =IF(OR(P17="",Q17=""),"",R16+(P17+Q17)) -> 299386.12 | S17: =IF(P17="","",SUM($P$3:P17)) -> 234433.29 | T17: =IF(S17="","",SUM($Q$3:Q17)) -> 64952.834 | V17: 6
D18: =IF(V18<=calcs!$F$4,'Loan Calculator'!V18,"") -> 7 | E18: {=_xlfn.IFS(F18="","",G17<F17,G17*calcs!$H$3,$D$8<=0,$M$3-F18,$D$8>0,$M$3-F18+$D$8,G17<F17,G18*calcs!$H$3)} -> 1451.0556 | F18: {=_xlfn.IFS(F17="","",G17=0,"",G17<1,"",G17<F17,G17,AND(G17>0,$D$8>0),$D$8+($M$3-(G17*calcs!$H$3)),G17>0,$M$3-(G17*calcs!$H$3))} -> 212.20062 | G18: {=_xlfn.IFS(F18="","",G17-F18<1,0,ISBLANK(F18)=TRUE,"",G17-F18>1,G17-F18)} -> 248540.19 | H18: =IF(OR(H17=0,H17="",E18="",F18=""),"",H17+E18+F18) -> 11642.794 | I18: {=_xlfn.IFS(OR(D18="",E18="",F18=""),"",MOD(D18,12)<>0,"",MOD(D18,12)=0,"Year End"&" "&D18/12)} | O18: =IF(AND(I203="",H192=""),"",16) -> 16 | P18: =IF(O18="","",SUBTOTAL(9,E192:E203)) -> 12724.105 | Q18: =IF(P18="","",SUBTOTAL(9,F192:F203)) -> 7234.9702 | R18: =IF(OR(P18="",Q18=""),"",R17+(P18+Q18)) -> 319345.2 | S18: =IF(P18="","",SUM($P$3:P18)) -> 247157.39 | T18: =IF(S18="","",SUM($Q$3:Q18)) -> 72187.805 | V18: 7
D19: =IF(V19<=calcs!$F$4,'Loan Calculator'!V19,"") -> 8 | E19: {=_xlfn.IFS(F19="","",G18<F18,G18*calcs!$H$3,$D$8<=0,$M$3-F19,$D$8>0,$M$3-F19+$D$8,G18<F18,G19*calcs!$H$3)} -> 1449.8178 | F19: {=_xlfn.IFS(F18="","",G18=0,"",G18<1,"",G18<F18,G18,AND(G18>0,$D$8>0),$D$8+($M$3-(G18*calcs!$H$3)),G18>0,$M$3-(G18*calcs!$H$3))} -> 213.43846 | G19: {=_xlfn.IFS(F19="","",G18-F19<1,0,ISBLANK(F19)=TRUE,"",G18-F19>1,G18-F19)} -> 248326.75 | H19: =IF(OR(H18=0,H18="",E19="",F19=""),"",H18+E19+F19) -> 13306.05 | I19: {=_xlfn.IFS(OR(D19="",E19="",F19=""),"",MOD(D19,12)<>0,"",MOD(D19,12)=0,"Year End"&" "&D19/12)} | O19: =IF(AND(I215="",H204=""),"",17) -> 17 | P19: =IF(O19="","",SUBTOTAL(9,E204:E215)) -> 12201.088 | Q19: =IF(P19="","",SUBTOTAL(9,F204:F215)) -> 7757.9868 | R19: =IF(OR(P19="",Q19=""),"",R18+(P19+Q19)) -> 339304.27 | S19: =IF(P19="","",SUM($P$3:P19)) -> 259358.48 | T19: =IF(S19="","",SUM($Q$3:Q19)) -> 79945.792 | V19: 8
D20: =IF(V20<=calcs!$F$4,'Loan Calculator'!V20,"") -> 9 | E20: {=_xlfn.IFS(F20="","",G19<F19,G19*calcs!$H$3,$D$8<=0,$M$3-F20,$D$8>0,$M$3-F20+$D$8,G19<F19,G20*calcs!$H$3)} -> 1448.5727 | F20: {=_xlfn.IFS(F19="","",G19=0,"",G19<1,"",G19<F19,G19,AND(G19>0,$D$8>0),$D$8+($M$3-(G19*calcs!$H$3)),G19>0,$M$3-(G19*calcs!$H$3))} -> 214.68351 | G20: {=_xlfn.IFS(F20="","",G19-F20<1,0,ISBLANK(F20)=TRUE,"",G19-F20>1,G19-F20)} -> 248112.07 | H20: =IF(OR(H19=0,H19="",E20="",F20=""),"",H19+E20+F20) -> 14969.306 | I20: {=_xlfn.IFS(OR(D20="",E20="",F20=""),"",MOD(D20,12)<>0,"",MOD(D20,12)=0,"Year End"&" "&D20/12)} | O20: =IF(AND(I227="",H216=""),"",18) -> 18 | P20: =IF(O20="","",SUBTOTAL(9,E216:E227)) -> 11640.263 | Q20: =IF(P20="","",SUBTOTAL(9,F216:F227)) -> 8318.8123 | R20: =IF(OR(P20="",Q20=""),"",R19+(P20+Q20)) -> 359263.35 | S20: =IF(P20="","",SUM($P$3:P20)) -> 270998.74 | T20: =IF(S20="","",SUM($Q$3:Q20)) -> 88264.604 | V20: 9
D21: =IF(V21<=calcs!$F$4,'Loan Calculator'!V21,"") -> 10 | E21: {=_xlfn.IFS(F21="","",G20<F20,G20*calcs!$H$3,$D$8<=0,$M$3-F21,$D$8>0,$M$3-F21+$D$8,G20<F20,G21*calcs!$H$3)} -> 1447.3204 | F21: {=_xlfn.IFS(F20="","",G20=0,"",G20<1,"",G20<F20,G20,AND(G20>0,$D$8>0),$D$8+($M$3-(G20*calcs!$H$3)),G20>0,$M$3-(G20*calcs!$H$3))} -> 215.93583 | G21: {=_xlfn.IFS(F21="","",G20-F21<1,0,ISBLANK(F21)=TRUE,"",G20-F21>1,G20-F21)} -> 247896.13 | H21: =IF(OR(H20=0,H20="",E21="",F21=""),"",H20+E21+F21) -> 16632.562 | I21: {=_xlfn.IFS(OR(D21="",E21="",F21=""),"",MOD(D21,12)<>0,"",MOD(D21,12)=0,"Year End"&" "&D21/12)} | O21: =IF(AND(I239="",H228=""),"",19) -> 19 | P21: =IF(O21="","",SUBTOTAL(9,E228:E239)) -> 11038.895 | Q21: =IF(P21="","",SUBTOTAL(9,F228:F239)) -> 8920.1799 | R21: =IF(OR(P21="",Q21=""),"",R20+(P21+Q21)) -> 379222.42 | S21: =IF(P21="","",SUM($P$3:P21)) -> 282037.64 | T21: =IF(S21="","",SUM($Q$3:Q21)) -> 97184.784 | V21: 10
D22: =IF(V22<=calcs!$F$4,'Loan Calculator'!V22,"") -> 11 | E22: {=_xlfn.IFS(F22="","",G21<F21,G21*calcs!$H$3,$D$8<=0,$M$3-F22,$D$8>0,$M$3-F22+$D$8,G21<F21,G22*calcs!$H$3)} -> 1446.0608 | F22: {=_xlfn.IFS(F21="","",G21=0,"",G21<1,"",G21<F21,G21,AND(G21>0,$D$8>0),$D$8+($M$3-(G21*calcs!$H$3)),G21>0,$M$3-(G21*calcs!$H$3))} -> 217.19546 | G22: {=_xlfn.IFS(F22="","",G21-F22<1,0,ISBLANK(F22)=TRUE,"",G21-F22>1,G21-F22)} -> 247678.94 | H22: =IF(OR(H21=0,H21="",E22="",F22=""),"",H21+E22+F22) -> 18295.819 | I22: {=_xlfn.IFS(OR(D22="",E22="",F22=""),"",MOD(D22,12)<>0,"",MOD(D22,12)=0,"Year End"&" "&D22/12)} | O22: =IF(AND(I251="",H240=""),"",20) -> 20 | P22: =IF(O22="","",SUBTOTAL(9,E240:E251)) -> 10394.054 | Q22: =IF(P22="","",SUBTOTAL(9,F240:F251)) -> 9565.0205 | R22: =IF(OR(P22="",Q22=""),"",R21+(P22+Q22)) -> 399181.5 | S22: =IF(P22="","",SUM($P$3:P22)) -> 292431.69 | T22: =IF(S22="","",SUM($Q$3:Q22)) -> 106749.8 | V22: 11
D23: =IF(V23<=calcs!$F$4,'Loan Calculator'!V23,"") -> 12 | E23: {=_xlfn.IFS(F23="","",G22<F22,G22*calcs!$H$3,$D$8<=0,$M$3-F23,$D$8>0,$M$3-F23+$D$8,G22<F22,G23*calcs!$H$3)} -> 1444.7938 | F23: {=_xlfn.IFS(F22="","",G22=0,"",G22<1,"",G22<F22,G22,AND(G22>0,$D$8>0),$D$8+($M$3-(G22*calcs!$H$3)),G22>0,$M$3-(G22*calcs!$H$3))} -> 218.46243 | G23: {=_xlfn.IFS(F23="","",G22-F23<1,0,ISBLANK(F23)=TRUE,"",G22-F23>1,G22-F23)} -> 247460.48 | H23: =IF(OR(H22=0,H22="",E23="",F23=""),"",H22+E23+F23) -> 19959.075 | I23: {=_xlfn.IFS(OR(D23="",E23="",F23=""),"",MOD(D23,12)<>0,"",MOD(D23,12)=0,"Year End"&" "&D23/12)} -> Year End 1 | O23: =IF(AND(I263="",H252=""),"",21) -> 21 | P23: =IF(O23="","",SUBTOTAL(9,E252:E263)) -> 9702.5983 | Q23: =IF(P23="","",SUBTOTAL(9,F252:F263)) -> 10256.477 | R23: =IF(OR(P23="",Q23=""),"",R22+(P23+Q23)) -> 419140.57 | S23: =IF(P23="","",SUM($P$3:P23)) -> 302134.29 | T23: =IF(S23="","",SUM($Q$3:Q23)) -> 117006.28 | V23: 12
D24: =IF(V24<=calcs!$F$4,'Loan Calculator'!V24,"") -> 13 | E24: {=_xlfn.IFS(F24="","",G23<F23,G23*calcs!$H$3,$D$8<=0,$M$3-F24,$D$8>0,$M$3-F24+$D$8,G23<F23,G24*calcs!$H$3)} -> 1443.5194 | F24: {=_xlfn.IFS(F23="","",G23=0,"",G23<1,"",G23<F23,G23,AND(G23>0,$D$8>0),$D$8+($M$3-(G23*calcs!$H$3)),G23>0,$M$3-(G23*calcs!$H$3))} -> 219.7368 | G24: {=_xlfn.IFS(F24="","",G23-F24<1,0,ISBLANK(F24)=TRUE,"",G23-F24>1,G23-F24)} -> 247240.74 | H24: =IF(OR(H23=0,H23="",E24="",F24=""),"",H23+E24+F24) -> 21622.331 | I24: {=_xlfn.IFS(OR(D24="",E24="",F24=""),"",MOD(D24,12)<>0,"",MOD(D24,12)=0,"Year End"&" "&D24/12)} | O24: =IF(AND(I275="",H264=""),"",22) -> 22 | P24: =IF(O24="","",SUBTOTAL(9,E264:E275)) -> 8961.1568 | Q24: =IF(P24="","",SUBTOTAL(9,F264:F275)) -> 10997.918 | R24: =IF(OR(P24="",Q24=""),"",R23+(P24+Q24)) -> 439099.65 | S24: =IF(P24="","",SUM($P$3:P24)) -> 311095.45 | T24: =IF(S24="","",SUM($Q$3:Q24)) -> 128004.2 | V24: 13
D25: =IF(V25<=calcs!$F$4,'Loan Calculator'!V25,"") -> 14 | E25: {=_xlfn.IFS(F25="","",G24<F24,G24*calcs!$H$3,$D$8<=0,$M$3-F25,$D$8>0,$M$3-F25+$D$8,G24<F24,G25*calcs!$H$3)} -> 1442.2376 | F25: {=_xlfn.IFS(F24="","",G24=0,"",G24<1,"",G24<F24,G24,AND(G24>0,$D$8>0),$D$8+($M$3-(G24*calcs!$H$3)),G24>0,$M$3-(G24*calcs!$H$3))} -> 221.0186 | G25: {=_xlfn.IFS(F25="","",G24-F25<1,0,ISBLANK(F25)=TRUE,"",G24-F25>1,G24-F25)} -> 247019.72 | H25: =IF(OR(H24=0,H24="",E25="",F25=""),"",H24+E25+F25) -> 23285.587 | I25: {=_xlfn.IFS(OR(D25="",E25="",F25=""),"",MOD(D25,12)<>0,"",MOD(D25,12)=0,"Year End"&" "&D25/12)} | O25: =IF(AND(I287="",H276=""),"",23) -> 23 | P25: =IF(O25="","",SUBTOTAL(9,E276:E287)) -> 8166.1164 | Q25: =IF(P25="","",SUBTOTAL(9,F276:F287)) -> 11792.958 | R25: =IF(OR(P25="",Q25=""),"",R24+(P25+Q25)) -> 459058.72 | S25: =IF(P25="","",SUM($P$3:P25)) -> 319261.56 | T25: =IF(S25="","",SUM($Q$3:Q25)) -> 139797.16 | V25: 14
D26: =IF(V26<=calcs!$F$4,'Loan Calculator'!V26,"") -> 15 | E26: {=_xlfn.IFS(F26="","",G25<F25,G25*calcs!$H$3,$D$8<=0,$M$3-F26,$D$8>0,$M$3-F26+$D$8,G25<F25,G26*calcs!$H$3)} -> 1440.9484 | F26: {=_xlfn.IFS(F25="","",G25=0,"",G25<1,"",G25<F25,G25,AND(G25>0,$D$8>0),$D$8+($M$3-(G25*calcs!$H$3)),G25>0,$M$3-(G25*calcs!$H$3))} -> 222.30787 | G26: {=_xlfn.IFS(F26="","",G25-F26<1,0,ISBLANK(F26)=TRUE,"",G25-F26>1,G25-F26)} -> 246797.41 | H26: =IF(OR(H25=0,H25="",E26="",F26=""),"",H25+E26+F26) -> 24948.844 | I26: {=_xlfn.IFS(OR(D26="",E26="",F26=""),"",MOD(D26,12)<>0,"",MOD(D26,12)=0,"Year End"&" "&D26/12)} | O26: =IF(AND(I299="",H388=""),"",24) -> 24 | P26: =IF(O26="","",SUBTOTAL(9,E288:E299)) -> 7313.6025 | Q26: =IF(P26="","",SUBTOTAL(9,F288:F299)) -> 12645.472 | R26: =IF(OR(P26="",Q26=""),"",R25+(P26+Q26)) -> 479017.8 | S26: =IF(P26="","",SUM($P$3:P26)) -> 326575.17 | T26: =IF(S26="","",SUM($Q$3:Q26)) -> 152442.63 | V26: 15
D27: =IF(V27<=calcs!$F$4,'Loan Calculator'!V27,"") -> 16 | E27: {=_xlfn.IFS(F27="","",G26<F26,G26*calcs!$H$3,$D$8<=0,$M$3-F27,$D$8>0,$M$3-F27+$D$8,G26<F26,G27*calcs!$H$3)} -> 1439.6516 | F27: {=_xlfn.IFS(F26="","",G26=0,"",G26<1,"",G26<F26,G26,AND(G26>0,$D$8>0),$D$8+($M$3-(G26*calcs!$H$3)),G26>0,$M$3-(G26*calcs!$H$3))} -> 223.60467 | G27: {=_xlfn.IFS(F27="","",G26-F27<1,0,ISBLANK(F27)=TRUE,"",G26-F27>1,G26-F27)} -> 246573.81 | H27: =IF(OR(H26=0,H26="",E27="",F27=""),"",H26+E27+F27) -> 26612.1 | I27: {=_xlfn.IFS(OR(D27="",E27="",F27=""),"",MOD(D27,12)<>0,"",MOD(D27,12)=0,"Year End"&" "&D27/12)} | O27: =IF(AND(I311="",H300=""),"",25) -> 25 | P27: =IF(O27="","",SUBTOTAL(9,E300:E311)) -> 6399.4603 | Q27: =IF(P27="","",SUBTOTAL(9,F300:F311)) -> 13559.615 | R27: =IF(OR(P27="",Q27=""),"",R26+(P27+Q27)) -> 498976.87 | S27: =IF(P27="","",SUM($P$3:P27)) -> 332974.63 | T27: =IF(S27="","",SUM($Q$3:Q27)) -> 166002.24 | V27: 16
D28: =IF(V28<=calcs!$F$4,'Loan Calculator'!V28,"") -> 17 | E28: {=_xlfn.IFS(F28="","",G27<F27,G27*calcs!$H$3,$D$8<=0,$M$3-F28,$D$8>0,$M$3-F28+$D$8,G27<F27,G28*calcs!$H$3)} -> 1438.3472 | F28: {=_xlfn.IFS(F27="","",G27=0,"",G27<1,"",G27<F27,G27,AND(G27>0,$D$8>0),$D$8+($M$3-(G27*calcs!$H$3)),G27>0,$M$3-(G27*calcs!$H$3))} -> 224.90903 | G28: {=_xlfn.IFS(F28="","",G27-F28<1,0,ISBLANK(F28)=TRUE,"",G27-F28>1,G27-F28)} -> 246348.9 | H28: =IF(OR(H27=0,H27="",E28="",F28=""),"",H27+E28+F28) -> 28275.356 | I28: {=_xlfn.IFS(OR(D28="",E28="",F28=""),"",MOD(D28,12)<>0,"",MOD(D28,12)=0,"Year End"&" "&D28/12)} | O28: =IF(AND(I323="",H312=""),"",26) -> 26 | P28: =IF(O28="","",SUBTOTAL(9,E312:E323)) -> 5419.2346 | Q28: =IF(P28="","",SUBTOTAL(9,F312:F323)) -> 14539.84 | R28: =IF(OR(P28="",Q28=""),"",R27+(P28+Q28)) -> 518935.95 | S28: =IF(P28="","",SUM($P$3:P28)) -> 338393.86 | T28: =IF(S28="","",SUM($Q$3:Q28)) -> 180542.08 | V28: 17
D29: =IF(V29<=calcs!$F$4,'Loan Calculator'!V29,"") -> 18 | E29: {=_xlfn.IFS(F29="","",G28<F28,G28*calcs!$H$3,$D$8<=0,$M$3-F29,$D$8>0,$M$3-F29+$D$8,G28<F28,G29*calcs!$H$3)} -> 1437.0352 | F29: {=_xlfn.IFS(F28="","",G28=0,"",G28<1,"",G28<F28,G28,AND(G28>0,$D$8>0),$D$8+($M$3-(G28*calcs!$H$3)),G28>0,$M$3-(G28*calcs!$H$3))} -> 226.221 | G29: {=_xlfn.IFS(F29="","",G28-F29<1,0,ISBLANK(F29)=TRUE,"",G28-F29>1,G28-F29)} -> 246122.68 | H29: =IF(OR(H28=0,H28="",E29="",F29=""),"",H28+E29+F29) -> 29938.612 | I29: {=_xlfn.IFS(OR(D29="",E29="",F29=""),"",MOD(D29,12)<>0,"",MOD(D29,12)=0,"Year End"&" "&D29/12)} | O29: =IF(AND(I335="",H324=""),"",27) -> 27 | P29: =IF(O29="","",SUBTOTAL(9,E324:E335)) -> 4368.1484 | Q29: =IF(P29="","",SUBTOTAL(9,F324:F335)) -> 15590.926 | R29: =IF(OR(P29="",Q29=""),"",R28+(P29+Q29)) -> 538895.02 | S29: =IF(P29="","",SUM($P$3:P29)) -> 342762.01 | T29: =IF(S29="","",SUM($Q$3:Q29)) -> 196133.01 | V29: 18
D30: =IF(V30<=calcs!$F$4,'Loan Calculator'!V30,"") -> 19 | E30: {=_xlfn.IFS(F30="","",G29<F29,G29*calcs!$H$3,$D$8<=0,$M$3-F30,$D$8>0,$M$3-F30+$D$8,G29<F29,G30*calcs!$H$3)} -> 1435.7156 | F30: {=_xlfn.IFS(F29="","",G29=0,"",G29<1,"",G29<F29,G29,AND(G29>0,$D$8>0),$D$8+($M$3-(G29*calcs!$H$3)),G29>0,$M$3-(G29*calcs!$H$3))} -> 227.54062 | G30: {=_xlfn.IFS(F30="","",G29-F30<1,0,ISBLANK(F30)=TRUE,"",G29-F30>1,G29-F30)} -> 245895.14 | H30: =IF(OR(H29=0,H29="",E30="",F30=""),"",H29+E30+F30) -> 31601.869 | I30: {=_xlfn.IFS(OR(D30="",E30="",F30=""),"",MOD(D30,12)<>0,"",MOD(D30,12)=0,"Year End"&" "&D30/12)} | O30: =IF(AND(I347="",H336=""),"",28) -> 28 | P30: =IF(O30="","",SUBTOTAL(9,E336:E347)) -> 3241.0791 | Q30: =IF(P30="","",SUBTOTAL(9,F336:F347)) -> 16717.996 | R30: =IF(OR(P30="",Q30=""),"",R29+(P30+Q30)) -> 558854.1 | S30: =IF(P30="","",SUM($P$3:P30)) -> 346003.09 | T30: =IF(S30="","",SUM($Q$3:Q30)) -> 212851.01 | V30: 19
D31: =IF(V31<=calcs!$F$4,'Loan Calculator'!V31,"") -> 20 | E31: {=_xlfn.IFS(F31="","",G30<F30,G30*calcs!$H$3,$D$8<=0,$M$3-F31,$D$8>0,$M$3-F31+$D$8,G30<F30,G31*calcs!$H$3)} -> 1434.3883 | F31: {=_xlfn.IFS(F30="","",G30=0,"",G30<1,"",G30<F30,G30,AND(G30>0,$D$8>0),$D$8+($M$3-(G30*calcs!$H$3)),G30>0,$M$3-(G30*calcs!$H$3))} -> 228.86794 | G31: {=_xlfn.IFS(F31="","",G30-F31<1,0,ISBLANK(F31)=TRUE,"",G30-F31>1,G30-F31)} -> 245666.27 | H31: =IF(OR(H30=0,H30="",E31="",F31=""),"",H30+E31+F31) -> 33265.125 | I31: {=_xlfn.IFS(OR(D31="",E31="",F31=""),"",MOD(D31,12)<>0,"",MOD(D31,12)=0,"Year End"&" "&D31/12)} | O31: =IF(AND(I359="",H348=""),"",29) -> 29 | P31: =IF(O31="","",SUBTOTAL(9,E348:E359)) -> 2032.5338 | Q31: =IF(P31="","",SUBTOTAL(9,F348:F359)) -> 17926.541 | R31: =IF(OR(P31="",Q31=""),"",R30+(P31+Q31)) -> 578813.17 | S31: =IF(P31="","",SUM($P$3:P31)) -> 348035.62 | T31: =IF(S31="","",SUM($Q$3:Q31)) -> 230777.55 | V31: 20
D32: =IF(V32<=calcs!$F$4,'Loan Calculator'!V32,"") -> 21 | E32: {=_xlfn.IFS(F32="","",G31<F31,G31*calcs!$H$3,$D$8<=0,$M$3-F32,$D$8>0,$M$3-F32+$D$8,G31<F31,G32*calcs!$H$3)} -> 1433.0532 | F32: {=_xlfn.IFS(F31="","",G31=0,"",G31<1,"",G31<F31,G31,AND(G31>0,$D$8>0),$D$8+($M$3-(G31*calcs!$H$3)),G31>0,$M$3-(G31*calcs!$H$3))} -> 230.203 | G32: {=_xlfn.IFS(F32="","",G31-F32<1,0,ISBLANK(F32)=TRUE,"",G31-F32>1,G31-F32)} -> 245436.07 | H32: =IF(OR(H31=0,H31="",E32="",F32=""),"",H31+E32+F32) -> 34928.381 | I32: {=_xlfn.IFS(OR(D32="",E32="",F32=""),"",MOD(D32,12)<>0,"",MOD(D32,12)=0,"Year End"&" "&D32/12)} | O32: =IF(AND(I371="",H360=""),"",30) -> 30 | P32: =IF(O32="","",SUBTOTAL(9,E360:E371)) -> 736.62269 | Q32: =IF(P32="","",SUBTOTAL(9,F360:F371)) -> 19222.452 | R32: =IF(OR(P32="",Q32=""),"",R31+(P32+Q32)) -> 598772.25 | S32: =IF(P32="","",SUM($P$3:P32)) -> 348772.25 | T32: =IF(S32="","",SUM($Q$3:Q32)) -> 250000 | V32: 21
D33: =IF(V33<=calcs!$F$4,'Loan Calculator'!V33,"") -> 22 | E33: {=_xlfn.IFS(F33="","",G32<F32,G32*calcs!$H$3,$D$8<=0,$M$3-F33,$D$8>0,$M$3-F33+$D$8,G32<F32,G33*calcs!$H$3)} -> 1431.7104 | F33: {=_xlfn.IFS(F32="","",G32=0,"",G32<1,"",G32<F32,G32,AND(G32>0,$D$8>0),$D$8+($M$3-(G32*calcs!$H$3)),G32>0,$M$3-(G32*calcs!$H$3))} -> 231.54585 | G33: {=_xlfn.IFS(F33="","",G32-F33<1,0,ISBLANK(F33)=TRUE,"",G32-F33>1,G32-F33)} -> 245204.52 | H33: =IF(OR(H32=0,H32="",E33="",F33=""),"",H32+E33+F33) -> 36591.637 | I33: {=_xlfn.IFS(OR(D33="",E33="",F33=""),"",MOD(D33,12)<>0,"",MOD(D33,12)=0,"Year End"&" "&D33/12)} | O33: =IF(AND(I383="",H372=""),"",31) | P33: =IF(O33="","",SUBTOTAL(9,E372:E383)) | Q33: =IF(P33="","",SUBTOTAL(9,F372:F383)) | R33: =IF(OR(P33="",Q33=""),"",R32+(P33+Q33)) | S33: =IF(P33="","",SUM($P$3:P33)) | T33: =IF(S33="","",SUM($Q$3:Q33)) | V33: 22
D34: =IF(V34<=calcs!$F$4,'Loan Calculator'!V34,"") -> 23 | E34: {=_xlfn.IFS(F34="","",G33<F33,G33*calcs!$H$3,$D$8<=0,$M$3-F34,$D$8>0,$M$3-F34+$D$8,G33<F33,G34*calcs!$H$3)} -> 1430.3597 | F34: {=_xlfn.IFS(F33="","",G33=0,"",G33<1,"",G33<F33,G33,AND(G33>0,$D$8>0),$D$8+($M$3-(G33*calcs!$H$3)),G33>0,$M$3-(G33*calcs!$H$3))} -> 232.89654 | G34: {=_xlfn.IFS(F34="","",G33-F34<1,0,ISBLANK(F34)=TRUE,"",G33-F34>1,G33-F34)} -> 244971.62 | H34: =IF(OR(H33=0,H33="",E34="",F34=""),"",H33+E34+F34) -> 38254.893 | I34: {=_xlfn.IFS(OR(D34="",E34="",F34=""),"",MOD(D34,12)<>0,"",MOD(D34,12)=0,"Year End"&" "&D34/12)} | O34: =IF(AND(I395="",H384=""),"",32) | P34: =IF(O34="","",SUBTOTAL(9,E384:E395)) | Q34: =IF(P34="","",SUBTOTAL(9,F384:F395)) | R34: =IF(OR(P34="",Q34=""),"",R33+(P34+Q34)) | S34: =IF(P34="","",SUM($P$3:P34)) | T34: =IF(S34="","",SUM($Q$3:Q34)) | V34: 23
D35: =IF(V35<=calcs!$F$4,'Loan Calculator'!V35,"") -> 24 | E35: {=_xlfn.IFS(F35="","",G34<F34,G34*calcs!$H$3,$D$8<=0,$M$3-F35,$D$8>0,$M$3-F35+$D$8,G34<F34,G35*calcs!$H$3)} -> 1429.0011 | F35: {=_xlfn.IFS(F34="","",G34=0,"",G34<1,"",G34<F34,G34,AND(G34>0,$D$8>0),$D$8+($M$3-(G34*calcs!$H$3)),G34>0,$M$3-(G34*calcs!$H$3))} -> 234.2551 | G35: {=_xlfn.IFS(F35="","",G34-F35<1,0,ISBLANK(F35)=TRUE,"",G34-F35>1,G34-F35)} -> 244737.37 | H35: =IF(OR(H34=0,H34="",E35="",F35=""),"",H34+E35+F35) -> 39918.15 | I35: {=_xlfn.IFS(OR(D35="",E35="",F35=""),"",MOD(D35,12)<>0,"",MOD(D35,12)=0,"Year End"&" "&D35/12)} -> Year End 2 | O35: =IF(AND(I407="",H396=""),"",33) | P35: =IF(O35="","",SUBTOTAL(9,E396:E407)) | Q35: =IF(P35="","",SUBTOTAL(9,F396:F407)) | R35: =IF(OR(P35="",Q35=""),"",R34+(P35+Q35)) | S35: =IF(P35="","",SUM($P$3:P35)) | T35: =IF(S35="","",SUM($Q$3:Q35)) | V35: 24
D36: =IF(V36<=calcs!$F$4,'Loan Calculator'!V36,"") -> 25 | E36: {=_xlfn.IFS(F36="","",G35<F35,G35*calcs!$H$3,$D$8<=0,$M$3-F36,$D$8>0,$M$3-F36+$D$8,G35<F35,G36*calcs!$H$3)} -> 1427.6346 | F36: {=_xlfn.IFS(F35="","",G35=0,"",G35<1,"",G35<F35,G35,AND(G35>0,$D$8>0),$D$8+($M$3-(G35*calcs!$H$3)),G35>0,$M$3-(G35*calcs!$H$3))} -> 235.62159 | G36: {=_xlfn.IFS(F36="","",G35-F36<1,0,ISBLANK(F36)=TRUE,"",G35-F36>1,G35-F36)} -> 244501.75 | H36: =IF(OR(H35=0,H35="",E36="",F36=""),"",H35+E36+F36) -> 41581.406 | I36: {=_xlfn.IFS(OR(D36="",E36="",F36=""),"",MOD(D36,12)<>0,"",MOD(D36,12)=0,"Year End"&" "&D36/12)} | O36: =IF(AND(I419="",H408=""),"",34) | P36: =IF(O36="","",SUBTOTAL(9,E408:E419)) | Q36: =IF(P36="","",SUBTOTAL(9,F408:F419)) | R36: =IF(OR(P36="",Q36=""),"",R35+(P36+Q36)) | S36: =IF(P36="","",SUM($P$3:P36)) | T36: =IF(S36="","",SUM($Q$3:Q36)) | V36: 25
D37: =IF(V37<=calcs!$F$4,'Loan Calculator'!V37,"") -> 26 | E37: {=_xlfn.IFS(F37="","",G36<F36,G36*calcs!$H$3,$D$8<=0,$M$3-F37,$D$8>0,$M$3-F37+$D$8,G36<F36,G37*calcs!$H$3)} -> 1426.2602 | F37: {=_xlfn.IFS(F36="","",G36=0,"",G36<1,"",G36<F36,G36,AND(G36>0,$D$8>0),$D$8+($M$3-(G36*calcs!$H$3)),G36>0,$M$3-(G36*calcs!$H$3))} -> 236.99605 | G37: {=_xlfn.IFS(F37="","",G36-F37<1,0,ISBLANK(F37)=TRUE,"",G36-F37>1,G36-F37)} -> 244264.75 | H37: =IF(OR(H36=0,H36="",E37="",F37=""),"",H36+E37+F37) -> 43244.662 | I37: {=_xlfn.IFS(OR(D37="",E37="",F37=""),"",MOD(D37,12)<>0,"",MOD(D37,12)=0,"Year End"&" "&D37/12)} | O37: =IF(AND(I431="",H420=""),"",35) | P37: =IF(O37="","",SUBTOTAL(9,E420:E431)) | Q37: =IF(P37="","",SUBTOTAL(9,F420:F431)) | R37: =IF(OR(P37="",Q37=""),"",R36+(P37+Q37)) | S37: =IF(P37="","",SUM($P$3:P37)) | T37: =IF(S37="","",SUM($Q$3:Q37)) | V37: 26
D38: =IF(V38<=calcs!$F$4,'Loan Calculator'!V38,"") -> 27 | E38: {=_xlfn.IFS(F38="","",G37<F37,G37*calcs!$H$3,$D$8<=0,$M$3-F38,$D$8>0,$M$3-F38+$D$8,G37<F37,G38*calcs!$H$3)} -> 1424.8777 | F38: {=_xlfn.IFS(F37="","",G37=0,"",G37<1,"",G37<F37,G37,AND(G37>0,$D$8>0),$D$8+($M$3-(G37*calcs!$H$3)),G37>0,$M$3-(G37*calcs!$H$3))} -> 238.37853 | G38: {=_xlfn.IFS(F38="","",G37-F38<1,0,ISBLANK(F38)=TRUE,"",G37-F38>1,G37-F38)} -> 244026.37 | H38: =IF(OR(H37=0,H37="",E38="",F38=""),"",H37+E38+F38) -> 44907.918 | I38: {=_xlfn.IFS(OR(D38="",E38="",F38=""),"",MOD(D38,12)<>0,"",MOD(D38,12)=0,"Year End"&" "&D38/12)} | O38: =IF(AND(I443="",H432=""),"",36) | P38: =IF(O38="","",SUBTOTAL(9,E432:E443)) | Q38: =IF(P38="","",SUBTOTAL(9,F432:F443)) | R38: =IF(OR(P38="",Q38=""),"",R37+(P38+Q38)) | S38: =IF(P38="","",SUM($P$3:P38)) | T38: =IF(S38="","",SUM($Q$3:Q38)) | V38: 27
D39: =IF(V39<=calcs!$F$4,'Loan Calculator'!V39,"") -> 28 | E39: {=_xlfn.IFS(F39="","",G38<F38,G38*calcs!$H$3,$D$8<=0,$M$3-F39,$D$8>0,$M$3-F39+$D$8,G38<F38,G39*calcs!$H$3)} -> 1423.4872 | F39: {=_xlfn.IFS(F38="","",G38=0,"",G38<1,"",G38<F38,G38,AND(G38>0,$D$8>0),$D$8+($M$3-(G38*calcs!$H$3)),G38>0,$M$3-(G38*calcs!$H$3))} -> 239.76907 | G39: {=_xlfn.IFS(F39="","",G38-F39<1,0,ISBLANK(F39)=TRUE,"",G38-F39>1,G38-F39)} -> 243786.6 | H39: =IF(OR(H38=0,H38="",E39="",F39=""),"",H38+E39+F39) -> 46571.175 | I39: {=_xlfn.IFS(OR(D39="",E39="",F39=""),"",MOD(D39,12)<>0,"",MOD(D39,12)=0,"Year End"&" "&D39/12)} | O39: =IF(AND(I455="",H444=""),"",37) | P39: =IF(O39="","",SUBTOTAL(9,E444:E455)) | Q39: =IF(P39="","",SUBTOTAL(9,F444:F455)) | R39: =IF(OR(P39="",Q39=""),"",R38+(P39+Q39)) | S39: =IF(P39="","",SUM($P$3:P39)) | T39: =IF(S39="","",SUM($Q$3:Q39)) | V39: 28
D40: =IF(V40<=calcs!$F$4,'Loan Calculator'!V40,"") -> 29 | E40: {=_xlfn.IFS(F40="","",G39<F39,G39*calcs!$H$3,$D$8<=0,$M$3-F40,$D$8>0,$M$3-F40+$D$8,G39<F39,G40*calcs!$H$3)} -> 1422.0885 | F40: {=_xlfn.IFS(F39="","",G39=0,"",G39<1,"",G39<F39,G39,AND(G39>0,$D$8>0),$D$8+($M$3-(G39*calcs!$H$3)),G39>0,$M$3-(G39*calcs!$H$3))} -> 241.16772 | G40: {=_xlfn.IFS(F40="","",G39-F40<1,0,ISBLANK(F40)=TRUE,"",G39-F40>1,G39-F40)} -> 243545.44 | H40: =IF(OR(H39=0,H39="",E40="",F40=""),"",H39+E40+F40) -> 48234.431 | I40: {=_xlfn.IFS(OR(D40="",E40="",F40=""),"",MOD(D40,12)<>0,"",MOD(D40,12)=0,"Year End"&" "&D40/12)} | O40: =IF(AND(I467="",H456=""),"",38) | P40: =IF(O40="","",SUBTOTAL(9,E456:E467)) | Q40: =IF(P40="","",SUBTOTAL(9,F456:F467)) | R40: =IF(OR(P40="",Q40=""),"",R39+(P40+Q40)) | S40: =IF(P40="","",SUM($P$3:P40)) | T40: =IF(S40="","",SUM($Q$3:Q40)) | V40: 29
D41: =IF(V41<=calcs!$F$4,'Loan Calculator'!V41,"") -> 30 | E41: {=_xlfn.IFS(F41="","",G40<F40,G40*calcs!$H$3,$D$8<=0,$M$3-F41,$D$8>0,$M$3-F41+$D$8,G40<F40,G41*calcs!$H$3)} -> 1420.6817 | F41: {=_xlfn.IFS(F40="","",G40=0,"",G40<1,"",G40<F40,G40,AND(G40>0,$D$8>0),$D$8+($M$3-(G40*calcs!$H$3)),G40>0,$M$3-(G40*calcs!$H$3))} -> 242.57453 | G41: {=_xlfn.IFS(F41="","",G40-F41<1,0,ISBLANK(F41)=TRUE,"",G40-F41>1,G40-F41)} -> 243302.86 | H41: =IF(OR(H40=0,H40="",E41="",F41=""),"",H40+E41+F41) -> 49897.687 | I41: {=_xlfn.IFS(OR(D41="",E41="",F41=""),"",MOD(D41,12)<>0,"",MOD(D41,12)=0,"Year End"&" "&D41/12)} | O41: =IF(AND(I479="",H468=""),"",39) | P41: =IF(O41="","",SUBTOTAL(9,E468:E479)) | Q41: =IF(P41="","",SUBTOTAL(9,F468:F479)) | R41: =IF(OR(P41="",Q41=""),"",R40+(P41+Q41)) | S41: =IF(P41="","",SUM($P$3:P41)) | T41: =IF(S41="","",SUM($Q$3:Q41)) | V41: 30
D42: =IF(V42<=calcs!$F$4,'Loan Calculator'!V42,"") -> 31 | E42: {=_xlfn.IFS(F42="","",G41<F41,G41*calcs!$H$3,$D$8<=0,$M$3-F42,$D$8>0,$M$3-F42+$D$8,G41<F41,G42*calcs!$H$3)} -> 1419.2667 | F42: {=_xlfn.IFS(F41="","",G41=0,"",G41<1,"",G41<F41,G41,AND(G41>0,$D$8>0),$D$8+($M$3-(G41*calcs!$H$3)),G41>0,$M$3-(G41*calcs!$H$3))} -> 243.98955 | G42: {=_xlfn.IFS(F42="","",G41-F42<1,0,ISBLANK(F42)=TRUE,"",G41-F42>1,G41-F42)} -> 243058.87 | H42: =IF(OR(H41=0,H41="",E42="",F42=""),"",H41+E42+F42) -> 51560.943 | I42: {=_xlfn.IFS(OR(D42="",E42="",F42=""),"",MOD(D42,12)<>0,"",MOD(D42,12)=0,"Year End"&" "&D42/12)} | O42: =IF(AND(I491="",H480=""),"",40) | P42: =IF(O42="","",SUBTOTAL(9,E480:E491)) | Q42: =IF(P42="","",SUBTOTAL(9,F480:F491)) | R42: =IF(OR(P42="",Q42=""),"",R41+(P42+Q42)) | S42: =IF(P42="","",SUM($P$3:P42)) | T42: =IF(S42="","",SUM($Q$3:Q42)) | V42: 31
D43: =IF(V43<=calcs!$F$4,'Loan Calculator'!V43,"") -> 32 | E43: {=_xlfn.IFS(F43="","",G42<F42,G42*calcs!$H$3,$D$8<=0,$M$3-F43,$D$8>0,$M$3-F43+$D$8,G42<F42,G43*calcs!$H$3)} -> 1417.8434 | F43: {=_xlfn.IFS(F42="","",G42=0,"",G42<1,"",G42<F42,G42,AND(G42>0,$D$8>0),$D$8+($M$3-(G42*calcs!$H$3)),G42>0,$M$3-(G42*calcs!$H$3))} -> 245.41282 | G43: {=_xlfn.IFS(F43="","",G42-F43<1,0,ISBLANK(F43)=TRUE,"",G42-F43>1,G42-F43)} -> 242813.46 | H43: =IF(OR(H42=0,H42="",E43="",F43=""),"",H42+E43+F43) -> 53224.2 | I43: {=_xlfn.IFS(OR(D43="",E43="",F43=""),"",MOD(D43,12)<>0,"",MOD(D43,12)=0,"Year End"&" "&D43/12)} | O43: =IF(AND(I503="",H492=""),"",41) | P43: =IF(O43="","",SUBTOTAL(9,E492:E503)) | Q43: =IF(P43="","",SUBTOTAL(9,F492:F503)) | R43: =IF(OR(P43="",Q43=""),"",R42+(P43+Q43)) | S43: =IF(P43="","",SUM($P$3:P43)) | T43: =IF(S43="","",SUM($Q$3:Q43)) | V43: 32
D44: =IF(V44<=calcs!$F$4,'Loan Calculator'!V44,"") -> 33 | E44: {=_xlfn.IFS(F44="","",G43<F43,G43*calcs!$H$3,$D$8<=0,$M$3-F44,$D$8>0,$M$3-F44+$D$8,G43<F43,G44*calcs!$H$3)} -> 1416.4118 | F44: {=_xlfn.IFS(F43="","",G43=0,"",G43<1,"",G43<F43,G43,AND(G43>0,$D$8>0),$D$8+($M$3-(G43*calcs!$H$3)),G43>0,$M$3-(G43*calcs!$H$3))} -> 246.8444 | G44: {=_xlfn.IFS(F44="","",G43-F44<1,0,ISBLANK(F44)=TRUE,"",G43-F44>1,G43-F44)} -> 242566.61 | H44: =IF(OR(H43=0,H43="",E44="",F44=""),"",H43+E44+F44) -> 54887.456 | I44: {=_xlfn.IFS(OR(D44="",E44="",F44=""),"",MOD(D44,12)<>0,"",MOD(D44,12)=0,"Year End"&" "&D44/12)} | O44: =IF(AND(I515="",H504=""),"",42) | P44: =IF(O44="","",SUBTOTAL(9,E504:E515)) | Q44: =IF(P44="","",SUBTOTAL(9,F504:F515)) | R44: =IF(OR(P44="",Q44=""),"",R43+(P44+Q44)) | S44: =IF(P44="","",SUM($P$3:P44)) | T44: =IF(S44="","",SUM($Q$3:Q44)) | V44: 33
D45: =IF(V45<=calcs!$F$4,'Loan Calculator'!V45,"") -> 34 | E45: {=_xlfn.IFS(F45="","",G44<F44,G44*calcs!$H$3,$D$8<=0,$M$3-F45,$D$8>0,$M$3-F45+$D$8,G44<F44,G45*calcs!$H$3)} -> 1414.9719 | F45: {=_xlfn.IFS(F44="","",G44=0,"",G44<1,"",G44<F44,G44,AND(G44>0,$D$8>0),$D$8+($M$3-(G44*calcs!$H$3)),G44>0,$M$3-(G44*calcs!$H$3))} -> 248.28432 | G45: {=_xlfn.IFS(F45="","",G44-F45<1,0,ISBLANK(F45)=TRUE,"",G44-F45>1,G44-F45)} -> 242318.33 | H45: =IF(OR(H44=0,H44="",E45="",F45=""),"",H44+E45+F45) -> 56550.712 | I45: {=_xlfn.IFS(OR(D45="",E45="",F45=""),"",MOD(D45,12)<>0,"",MOD(D45,12)=0,"Year End"&" "&D45/12)} | O45: =IF(AND(I527="",H516=""),"",43) | P45: =IF(O45="","",SUBTOTAL(9,E516:E527)) | Q45: =IF(P45="","",SUBTOTAL(9,F516:F527)) | R45: =IF(OR(P45="",Q45=""),"",R44+(P45+Q45)) | S45: =IF(P45="","",SUM($P$3:P45)) | T45: =IF(S45="","",SUM($Q$3:Q45)) | V45: 34
D46: =IF(V46<=calcs!$F$4,'Loan Calculator'!V46,"") -> 35 | E46: {=_xlfn.IFS(F46="","",G45<F45,G45*calcs!$H$3,$D$8<=0,$M$3-F46,$D$8>0,$M$3-F46+$D$8,G45<F45,G46*calcs!$H$3)} -> 1413.5236 | F46: {=_xlfn.IFS(F45="","",G45=0,"",G45<1,"",G45<F45,G45,AND(G45>0,$D$8>0),$D$8+($M$3-(G45*calcs!$H$3)),G45>0,$M$3-(G45*calcs!$H$3))} -> 249.73265 | G46: {=_xlfn.IFS(F46="","",G45-F46<1,0,ISBLANK(F46)=TRUE,"",G45-F46>1,G45-F46)} -> 242068.6 | H46: =IF(OR(H45=0,H45="",E46="",F46=""),"",H45+E46+F46) -> 58213.968 | I46: {=_xlfn.IFS(OR(D46="",E46="",F46=""),"",MOD(D46,12)<>0,"",MOD(D46,12)=0,"Year End"&" "&D46/12)} | O46: =IF(AND(I539="",H528=""),"",44) | P46: =IF(O46="","",SUBTOTAL(9,E528:E539)) | Q46: =IF(P46="","",SUBTOTAL(9,F528:F539)) | R46: =IF(OR(P46="",Q46=""),"",R45+(P46+Q46)) | S46: =IF(P46="","",SUM($P$3:P46)) | T46: =IF(S46="","",SUM($Q$3:Q46)) | V46: 35
D47: =IF(V47<=calcs!$F$4,'Loan Calculator'!V47,"") -> 36 | E47: {=_xlfn.IFS(F47="","",G46<F46,G46*calcs!$H$3,$D$8<=0,$M$3-F47,$D$8>0,$M$3-F47+$D$8,G46<F46,G47*calcs!$H$3)} -> 1412.0668 | F47: {=_xlfn.IFS(F46="","",G46=0,"",G46<1,"",G46<F46,G46,AND(G46>0,$D$8>0),$D$8+($M$3-(G46*calcs!$H$3)),G46>0,$M$3-(G46*calcs!$H$3))} -> 251.18942 | G47: {=_xlfn.IFS(F47="","",G46-F47<1,0,ISBLANK(F47)=TRUE,"",G46-F47>1,G46-F47)} -> 241817.41 | H47: =IF(OR(H46=0,H46="",E47="",F47=""),"",H46+E47+F47) -> 59877.225 | I47: {=_xlfn.IFS(OR(D47="",E47="",F47=""),"",MOD(D47,12)<>0,"",MOD(D47,12)=0,"Year End"&" "&D47/12)} -> Year End 3 | O47: =IF(AND(I551="",H540=""),"",45) | P47: =IF(O47="","",SUBTOTAL(9,E540:E551)) | Q47: =IF(P47="","",SUBTOTAL(9,F540:F551)) | R47: =IF(OR(P47="",Q47=""),"",R46+(P47+Q47)) | S47: =IF(P47="","",SUM($P$3:P47)) | T47: =IF(S47="","",SUM($Q$3:Q47)) | V47: 36
D48: =IF(V48<=calcs!$F$4,'Loan Calculator'!V48,"") -> 37 | E48: {=_xlfn.IFS(F48="","",G47<F47,G47*calcs!$H$3,$D$8<=0,$M$3-F48,$D$8>0,$M$3-F48+$D$8,G47<F47,G48*calcs!$H$3)} -> 1410.6015 | F48: {=_xlfn.IFS(F47="","",G47=0,"",G47<1,"",G47<F47,G47,AND(G47>0,$D$8>0),$D$8+($M$3-(G47*calcs!$H$3)),G47>0,$M$3-(G47*calcs!$H$3))} -> 252.65469 | G48: {=_xlfn.IFS(F48="","",G47-F48<1,0,ISBLANK(F48)=TRUE,"",G47-F48>1,G47-F48)} -> 241564.75 | H48: =IF(OR(H47=0,H47="",E48="",F48=""),"",H47+E48+F48) -> 61540.481 | I48: {=_xlfn.IFS(OR(D48="",E48="",F48=""),"",MOD(D48,12)<>0,"",MOD(D48,12)=0,"Year End"&" "&D48/12)} | O48: =IF(AND(I563="",H552=""),"",46) | P48: =IF(O48="","",SUBTOTAL(9,E552:E563)) | Q48: =IF(P48="","",SUBTOTAL(9,F552:F563)) | R48: =IF(OR(P48="",Q48=""),"",R47+(P48+Q48)) | S48: =IF(P48="","",SUM($P$3:P48)) | T48: =IF(S48="","",SUM($Q$3:Q48)) | V48: 37
D49: =IF(V49<=calcs!$F$4,'Loan Calculator'!V49,"") -> 38 | E49: {=_xlfn.IFS(F49="","",G48<F48,G48*calcs!$H$3,$D$8<=0,$M$3-F49,$D$8>0,$M$3-F49+$D$8,G48<F48,G49*calcs!$H$3)} -> 1409.1277 | F49: {=_xlfn.IFS(F48="","",G48=0,"",G48<1,"",G48<F48,G48,AND(G48>0,$D$8>0),$D$8+($M$3-(G48*calcs!$H$3)),G48>0,$M$3-(G48*calcs!$H$3))} -> 254.12851 | G49: {=_xlfn.IFS(F49="","",G48-F49<1,0,ISBLANK(F49)=TRUE,"",G48-F49>1,G48-F49)} -> 241310.62 | H49: =IF(OR(H48=0,H48="",E49="",F49=""),"",H48+E49+F49) -> 63203.737 | I49: {=_xlfn.IFS(OR(D49="",E49="",F49=""),"",MOD(D49,12)<>0,"",MOD(D49,12)=0,"Year End"&" "&D49/12)} | O49: =IF(AND(I575="",H564=""),"",47) | P49: =IF(O49="","",SUBTOTAL(9,E564:E575)) | Q49: =IF(P49="","",SUBTOTAL(9,F564:F575)) | R49: =IF(OR(P49="",Q49=""),"",R48+(P49+Q49)) | S49: =IF(P49="","",SUM($P$3:P49)) | T49: =IF(S49="","",SUM($Q$3:Q49)) | V49: 38
D50: =IF(V50<=calcs!$F$4,'Loan Calculator'!V50,"") -> 39 | E50: {=_xlfn.IFS(F50="","",G49<F49,G49*calcs!$H$3,$D$8<=0,$M$3-F50,$D$8>0,$M$3-F50+$D$8,G49<F49,G50*calcs!$H$3)} -> 1407.6453 | F50: {=_xlfn.IFS(F49="","",G49=0,"",G49<1,"",G49<F49,G49,AND(G49>0,$D$8>0),$D$8+($M$3-(G49*calcs!$H$3)),G49>0,$M$3-(G49*calcs!$H$3))} -> 255.61093 | G50: {=_xlfn.IFS(F50="","",G49-F50<1,0,ISBLANK(F50)=TRUE,"",G49-F50>1,G49-F50)} -> 241055.01 | H50: =IF(OR(H49=0,H49="",E50="",F50=""),"",H49+E50+F50) -> 64866.993 | I50: {=_xlfn.IFS(OR(D50="",E50="",F50=""),"",MOD(D50,12)<>0,"",MOD(D50,12)=0,"Year End"&" "&D50/12)} | O50: =IF(AND(I587="",H576=""),"",48) | P50: =IF(O50="","",SUBTOTAL(9,E576:E587)) | Q50: =IF(P50="","",SUBTOTAL(9,F576:F587)) | R50: =IF(OR(P50="",Q50=""),"",R49+(P50+Q50)) | S50: =IF(P50="","",SUM($P$3:P50)) | T50: =IF(S50="","",SUM($Q$3:Q50)) | V50: 39
D51: =IF(V51<=calcs!$F$4,'Loan Calculator'!V51,"") -> 40 | E51: {=_xlfn.IFS(F51="","",G50<F50,G50*calcs!$H$3,$D$8<=0,$M$3-F51,$D$8>0,$M$3-F51+$D$8,G50<F50,G51*calcs!$H$3)} -> 1406.1542 | F51: {=_xlfn.IFS(F50="","",G50=0,"",G50<1,"",G50<F50,G50,AND(G50>0,$D$8>0),$D$8+($M$3-(G50*calcs!$H$3)),G50>0,$M$3-(G50*calcs!$H$3))} -> 257.10199 | G51: {=_xlfn.IFS(F51="","",G50-F51<1,0,ISBLANK(F51)=TRUE,"",G50-F51>1,G50-F51)} -> 240797.91 | H51: =IF(OR(H50=0,H50="",E51="",F51=""),"",H50+E51+F51) -> 66530.25 | I51: {=_xlfn.IFS(OR(D51="",E51="",F51=""),"",MOD(D51,12)<>0,"",MOD(D51,12)=0,"Year End"&" "&D51/12)} | O51: =IF(AND(I599="",H588=""),"",49) | P51: =IF(O51="","",SUBTOTAL(9,E588:E599)) | Q51: =IF(P51="","",SUBTOTAL(9,F588:F599)) | R51: =IF(OR(P51="",Q51=""),"",R50+(P51+Q51)) | S51: =IF(P51="","",SUM($P$3:P51)) | T51: =IF(S51="","",SUM($Q$3:Q51)) | V51: 40
D52: =IF(V52<=calcs!$F$4,'Loan Calculator'!V52,"") -> 41 | E52: {=_xlfn.IFS(F52="","",G51<F51,G51*calcs!$H$3,$D$8<=0,$M$3-F52,$D$8>0,$M$3-F52+$D$8,G51<F51,G52*calcs!$H$3)} -> 1404.6545 | F52: {=_xlfn.IFS(F51="","",G51=0,"",G51<1,"",G51<F51,G51,AND(G51>0,$D$8>0),$D$8+($M$3-(G51*calcs!$H$3)),G51>0,$M$3-(G51*calcs!$H$3))} -> 258.60175 | G52: {=_xlfn.IFS(F52="","",G51-F52<1,0,ISBLANK(F52)=TRUE,"",G51-F52>1,G51-F52)} -> 240539.31 | H52: =IF(OR(H51=0,H51="",E52="",F52=""),"",H51+E52+F52) -> 68193.506 | I52: {=_xlfn.IFS(OR(D52="",E52="",F52=""),"",MOD(D52,12)<>0,"",MOD(D52,12)=0,"Year End"&" "&D52/12)} | O52: =IF(I611="","",50) | P52: =IF(O52="","",SUBTOTAL(9,E600:E611)) | Q52: =IF(P52="","",SUBTOTAL(9,F600:F611)) | R52: =IF(OR(P52="",Q52=""),"",R51+(P52+Q52)) | S52: =IF(P52="","",SUM($P$3:P52)) | T52: =IF(S52="","",SUM($Q$3:Q52)) | V52: 41
D53: =IF(V53<=calcs!$F$4,'Loan Calculator'!V53,"") -> 42 | E53: {=_xlfn.IFS(F53="","",G52<F52,G52*calcs!$H$3,$D$8<=0,$M$3-F53,$D$8>0,$M$3-F53+$D$8,G52<F52,G53*calcs!$H$3)} -> 1403.146 | F53: {=_xlfn.IFS(F52="","",G52=0,"",G52<1,"",G52<F52,G52,AND(G52>0,$D$8>0),$D$8+($M$3-(G52*calcs!$H$3)),G52>0,$M$3-(G52*calcs!$H$3))} -> 260.11026 | G53: {=_xlfn.IFS(F53="","",G52-F53<1,0,ISBLANK(F53)=TRUE,"",G52-F53>1,G52-F53)} -> 240279.2 | H53: =IF(OR(H52=0,H52="",E53="",F53=""),"",H52+E53+F53) -> 69856.762 | I53: {=_xlfn.IFS(OR(D53="",E53="",F53=""),"",MOD(D53,12)<>0,"",MOD(D53,12)=0,"Year End"&" "&D53/12)} | V53: 42
D54: =IF(V54<=calcs!$F$4,'Loan Calculator'!V54,"") -> 43 | E54: {=_xlfn.IFS(F54="","",G53<F53,G53*calcs!$H$3,$D$8<=0,$M$3-F54,$D$8>0,$M$3-F54+$D$8,G53<F53,G54*calcs!$H$3)} -> 1401.6287 | F54: {=_xlfn.IFS(F53="","",G53=0,"",G53<1,"",G53<F53,G53,AND(G53>0,$D$8>0),$D$8+($M$3-(G53*calcs!$H$3)),G53>0,$M$3-(G53*calcs!$H$3))} -> 261.62757 | G54: {=_xlfn.IFS(F54="","",G53-F54<1,0,ISBLANK(F54)=TRUE,"",G53-F54>1,G53-F54)} -> 240017.57 | H54: =IF(OR(H53=0,H53="",E54="",F54=""),"",H53+E54+F54) -> 71520.018 | I54: {=_xlfn.IFS(OR(D54="",E54="",F54=""),"",MOD(D54,12)<>0,"",MOD(D54,12)=0,"Year End"&" "&D54/12)} | V54: 43
D55: =IF(V55<=calcs!$F$4,'Loan Calculator'!V55,"") -> 44 | E55: {=_xlfn.IFS(F55="","",G54<F54,G54*calcs!$H$3,$D$8<=0,$M$3-F55,$D$8>0,$M$3-F55+$D$8,G54<F54,G55*calcs!$H$3)} -> 1400.1025 | F55: {=_xlfn.IFS(F54="","",G54=0,"",G54<1,"",G54<F54,G54,AND(G54>0,$D$8>0),$D$8+($M$3-(G54*calcs!$H$3)),G54>0,$M$3-(G54*calcs!$H$3))} -> 263.15373 | G55: {=_xlfn.IFS(F55="","",G54-F55<1,0,ISBLANK(F55)=TRUE,"",G54-F55>1,G54-F55)} -> 239754.42 | H55: =IF(OR(H54=0,H54="",E55="",F55=""),"",H54+E55+F55) -> 73183.274 | I55: {=_xlfn.IFS(OR(D55="",E55="",F55=""),"",MOD(D55,12)<>0,"",MOD(D55,12)=0,"Year End"&" "&D55/12)} | V55: 44
D56: =IF(V56<=calcs!$F$4,'Loan Calculator'!V56,"") -> 45 | E56: {=_xlfn.IFS(F56="","",G55<F55,G55*calcs!$H$3,$D$8<=0,$M$3-F56,$D$8>0,$M$3-F56+$D$8,G55<F55,G56*calcs!$H$3)} -> 1398.5674 | F56: {=_xlfn.IFS(F55="","",G55=0,"",G55<1,"",G55<F55,G55,AND(G55>0,$D$8>0),$D$8+($M$3-(G55*calcs!$H$3)),G55>0,$M$3-(G55*calcs!$H$3))} -> 264.6888 | G56: {=_xlfn.IFS(F56="","",G55-F56<1,0,ISBLANK(F56)=TRUE,"",G55-F56>1,G55-F56)} -> 239489.73 | H56: =IF(OR(H55=0,H55="",E56="",F56=""),"",H55+E56+F56) -> 74846.531 | I56: {=_xlfn.IFS(OR(D56="",E56="",F56=""),"",MOD(D56,12)<>0,"",MOD(D56,12)=0,"Year End"&" "&D56/12)} | V56: 45
D57: =IF(V57<=calcs!$F$4,'Loan Calculator'!V57,"") -> 46 | E57: {=_xlfn.IFS(F57="","",G56<F56,G56*calcs!$H$3,$D$8<=0,$M$3-F57,$D$8>0,$M$3-F57+$D$8,G56<F56,G57*calcs!$H$3)} -> 1397.0234 | F57: {=_xlfn.IFS(F56="","",G56=0,"",G56<1,"",G56<F56,G56,AND(G56>0,$D$8>0),$D$8+($M$3-(G56*calcs!$H$3)),G56>0,$M$3-(G56*calcs!$H$3))} -> 266.23282 | G57: {=_xlfn.IFS(F57="","",G56-F57<1,0,ISBLANK(F57)=TRUE,"",G56-F57>1,G56-F57)} -> 239223.5 | H57: =IF(OR(H56=0,H56="",E57="",F57=""),"",H56+E57+F57) -> 76509.787 | I57: {=_xlfn.IFS(OR(D57="",E57="",F57=""),"",MOD(D57,12)<>0,"",MOD(D57,12)=0,"Year End"&" "&D57/12)} | V57: 46
D58: =IF(V58<=calcs!$F$4,'Loan Calculator'!V58,"") -> 47 | E58: {=_xlfn.IFS(F58="","",G57<F57,G57*calcs!$H$3,$D$8<=0,$M$3-F58,$D$8>0,$M$3-F58+$D$8,G57<F57,G58*calcs!$H$3)} -> 1395.4704 | F58: {=_xlfn.IFS(F57="","",G57=0,"",G57<1,"",G57<F57,G57,AND(G57>0,$D$8>0),$D$8+($M$3-(G57*calcs!$H$3)),G57>0,$M$3-(G57*calcs!$H$3))} -> 267.78584 | G58: {=_xlfn.IFS(F58="","",G57-F58<1,0,ISBLANK(F58)=TRUE,"",G57-F58>1,G57-F58)} -> 238955.71 | H58: =IF(OR(H57=0,H57="",E58="",F58=""),"",H57+E58+F58) -> 78173.043 | I58: {=_xlfn.IFS(OR(D58="",E58="",F58=""),"",MOD(D58,12)<>0,"",MOD(D58,12)=0,"Year End"&" "&D58/12)} | V58: 47
D59: =IF(V59<=calcs!$F$4,'Loan Calculator'!V59,"") -> 48 | E59: {=_xlfn.IFS(F59="","",G58<F58,G58*calcs!$H$3,$D$8<=0,$M$3-F59,$D$8>0,$M$3-F59+$D$8,G58<F58,G59*calcs!$H$3)} -> 1393.9083 | F59: {=_xlfn.IFS(F58="","",G58=0,"",G58<1,"",G58<F58,G58,AND(G58>0,$D$8>0),$D$8+($M$3-(G58*calcs!$H$3)),G58>0,$M$3-(G58*calcs!$H$3))} -> 269.34792 | G59: {=_xlfn.IFS(F59="","",G58-F59<1,0,ISBLANK(F59)=TRUE,"",G58-F59>1,G58-F59)} -> 238686.36 | H59: =IF(OR(H58=0,H58="",E59="",F59=""),"",H58+E59+F59) -> 79836.299 | I59: {=_xlfn.IFS(OR(D59="",E59="",F59=""),"",MOD(D59,12)<>0,"",MOD(D59,12)=0,"Year End"&" "&D59/12)} -> Year End 4 | V59: 48
D60: =IF(V60<=calcs!$F$4,'Loan Calculator'!V60,"") -> 49 | E60: {=_xlfn.IFS(F60="","",G59<F59,G59*calcs!$H$3,$D$8<=0,$M$3-F60,$D$8>0,$M$3-F60+$D$8,G59<F59,G60*calcs!$H$3)} -> 1392.3371 | F60: {=_xlfn.IFS(F59="","",G59=0,"",G59<1,"",G59<F59,G59,AND(G59>0,$D$8>0),$D$8+($M$3-(G59*calcs!$H$3)),G59>0,$M$3-(G59*calcs!$H$3))} -> 270.91912 | G60: {=_xlfn.IFS(F60="","",G59-F60<1,0,ISBLANK(F60)=TRUE,"",G59-F60>1,G59-F60)} -> 238415.44 | H60: =IF(OR(H59=0,H59="",E60="",F60=""),"",H59+E60+F60) -> 81499.556 | I60: {=_xlfn.IFS(OR(D60="",E60="",F60=""),"",MOD(D60,12)<>0,"",MOD(D60,12)=0,"Year End"&" "&D60/12)} | V60: 49
D61: =IF(V61<=calcs!$F$4,'Loan Calculator'!V61,"") -> 50 | E61: {=_xlfn.IFS(F61="","",G60<F60,G60*calcs!$H$3,$D$8<=0,$M$3-F61,$D$8>0,$M$3-F61+$D$8,G60<F60,G61*calcs!$H$3)} -> 1390.7568 | F61: {=_xlfn.IFS(F60="","",G60=0,"",G60<1,"",G60<F60,G60,AND(G60>0,$D$8>0),$D$8+($M$3-(G60*calcs!$H$3)),G60>0,$M$3-(G60*calcs!$H$3))} -> 272.49948 | G61: {=_xlfn.IFS(F61="","",G60-F61<1,0,ISBLANK(F61)=TRUE,"",G60-F61>1,G60-F61)} -> 238142.94 | H61: =IF(OR(H60=0,H60="",E61="",F61=""),"",H60+E61+F61) -> 83162.812 | I61: {=_xlfn.IFS(OR(D61="",E61="",F61=""),"",MOD(D61,12)<>0,"",MOD(D61,12)=0,"Year End"&" "&D61/12)} | V61: 50
D62: =IF(V62<=calcs!$F$4,'Loan Calculator'!V62,"") -> 51 | E62: {=_xlfn.IFS(F62="","",G61<F61,G61*calcs!$H$3,$D$8<=0,$M$3-F62,$D$8>0,$M$3-F62+$D$8,G61<F61,G62*calcs!$H$3)} -> 1389.1672 | F62: {=_xlfn.IFS(F61="","",G61=0,"",G61<1,"",G61<F61,G61,AND(G61>0,$D$8>0),$D$8+($M$3-(G61*calcs!$H$3)),G61>0,$M$3-(G61*calcs!$H$3))} -> 274.08906 | G62: {=_xlfn.IFS(F62="","",G61-F62<1,0,ISBLANK(F62)=TRUE,"",G61-F62>1,G61-F62)} -> 237868.86 | H62: =IF(OR(H61=0,H61="",E62="",F62=""),"",H61+E62+F62) -> 84826.068 | I62: {=_xlfn.IFS(OR(D62="",E62="",F62=""),"",MOD(D62,12)<>0,"",MOD(D62,12)=0,"Year End"&" "&D62/12)} | V62: 51
D63: =IF(V63<=calcs!$F$4,'Loan Calculator'!V63,"") -> 52 | E63: {=_xlfn.IFS(F63="","",G62<F62,G62*calcs!$H$3,$D$8<=0,$M$3-F63,$D$8>0,$M$3-F63+$D$8,G62<F62,G63*calcs!$H$3)} -> 1387.5683 | F63: {=_xlfn.IFS(F62="","",G62=0,"",G62<1,"",G62<F62,G62,AND(G62>0,$D$8>0),$D$8+($M$3-(G62*calcs!$H$3)),G62>0,$M$3-(G62*calcs!$H$3))} -> 275.68792 | G63: {=_xlfn.IFS(F63="","",G62-F63<1,0,ISBLANK(F63)=TRUE,"",G62-F63>1,G62-F63)} -> 237593.17 | H63: =IF(OR(H62=0,H62="",E63="",F63=""),"",H62+E63+F63) -> 86489.324 | I63: {=_xlfn.IFS(OR(D63="",E63="",F63=""),"",MOD(D63,12)<>0,"",MOD(D63,12)=0,"Year End"&" "&D63/12)} | V63: 52
D64: =IF(V64<=calcs!$F$4,'Loan Calculator'!V64,"") -> 53 | E64: {=_xlfn.IFS(F64="","",G63<F63,G63*calcs!$H$3,$D$8<=0,$M$3-F64,$D$8>0,$M$3-F64+$D$8,G63<F63,G64*calcs!$H$3)} -> 1385.9601 | F64: {=_xlfn.IFS(F63="","",G63=0,"",G63<1,"",G63<F63,G63,AND(G63>0,$D$8>0),$D$8+($M$3-(G63*calcs!$H$3)),G63>0,$M$3-(G63*calcs!$H$3))} -> 277.29609 | G64: {=_xlfn.IFS(F64="","",G63-F64<1,0,ISBLANK(F64)=TRUE,"",G63-F64>1,G63-F64)} -> 237315.87 | H64: =IF(OR(H63=0,H63="",E64="",F64=""),"",H63+E64+F64) -> 88152.581 | I64: {=_xlfn.IFS(OR(D64="",E64="",F64=""),"",MOD(D64,12)<>0,"",MOD(D64,12)=0,"Year End"&" "&D64/12)} | V64: 53
... D1011: =IF(V1011<=calcs!$F$4,'Loan Calculator'!V1011,"") | E1011: {=_xlfn.IFS(F1011="","",G1010<F1010,G1010*calcs!$H$3,$D$8<=0,$M$3-F1011,$D$8>0,$M$3-F1011+$D$8,G1010<F1010,G1011*calcs!$H$3)} | F1011: {=_xlfn.IFS(F1010="","",G1010=0,"",G1010<1,"",G1010<F1010,G1010,AND(G1010>0,$D$8>0),$D$8+($M$3-(G1010*calcs!$H$3)),G1010>0,$M$3-(G1010*calcs!$H$3))} | G1011: {=_xlfn.IFS(F1011="","",G1010-F1011<1,0,ISBLANK(F1011)=TRUE,"",G1010-F1011>1,G1010-F1011)} | H1011: =IF(OR(H1010=0,H1010="",E1011="",F1011=""),"",H1010+E1011+F1011) | I1011: {=_xlfn.IFS(OR(D1011="",E1011="",F1011=""),"",MOD(D1011,12)<>0,"",MOD(D1011,12)=0,"Year End"&" "&D1011/12)} | V1011: 1000

Sheet calcs
A1: Calculations
D2: Years | E2: Months | H2: Interest rate per period | M2: .
D3: ='Loan Calculator'!B3 -> 30 | H3: ='Loan Calculator'!I3/12 -> 0.0058333333
C4: Covert to months | D4: =D3*12 -> 360 | E4: ='Loan Calculator'!B4 -> 0 | F4: =D4+E4 -> 360
F5: Total months
H7: Payment per Period | I7: Numerator | J7: Denominator
H8: ='Loan Calculator'!F3*calcs!J11 -> 1663.2562 | I8: =H3*(1+H3)^F4 -> 0.047346235 | J8: =(1+H3)^F4-1 -> 7.1164975
J10: Equates to
J11: =I8/J8 -> 0.006653025
H14: Beginning interest pmt | I14: Beginning Priciple pmt
H15: =H8-I15 -> 1458.3333 | I15: =H8-('Loan Calculator'!F3*calcs!H3) -> 204.9229
